odoo8_addon_account_invoice_rounding-8.0.1.1.1-py2.7-nspkg.pth
odoo8_addon_account_invoice_rounding-8.0.1.1.1.dist-info/DESCRIPTION.rst
odoo8_addon_account_invoice_rounding-8.0.1.1.1.dist-info/METADATA
odoo8_addon_account_invoice_rounding-8.0.1.1.1.dist-info/RECORD
odoo8_addon_account_invoice_rounding-8.0.1.1.1.dist-info/WHEEL
odoo8_addon_account_invoice_rounding-8.0.1.1.1.dist-info/metadata.json
odoo8_addon_account_invoice_rounding-8.0.1.1.1.dist-info/namespace_packages.txt
odoo8_addon_account_invoice_rounding-8.0.1.1.1.dist-info/top_level.txt
odoo_addons/account_invoice_rounding/README.rst
odoo_addons/account_invoice_rounding/__init__.py
odoo_addons/account_invoice_rounding/__openerp__.py
odoo_addons/account_invoice_rounding/account.py
odoo_addons/account_invoice_rounding/account_invoice_view.xml
odoo_addons/account_invoice_rounding/company.py
odoo_addons/account_invoice_rounding/partner.py
odoo_addons/account_invoice_rounding/res_config.py
odoo_addons/account_invoice_rounding/res_config_view.xml
odoo_addons/account_invoice_rounding/res_partner_view.xml
odoo_addons/account_invoice_rounding/documentation/DOC_l10n_ch_5cts_roundings.ods
odoo_addons/account_invoice_rounding/i18n/account_invoice_rounding.pot
odoo_addons/account_invoice_rounding/i18n/am.po
odoo_addons/account_invoice_rounding/i18n/ar.po
odoo_addons/account_invoice_rounding/i18n/bg.po
odoo_addons/account_invoice_rounding/i18n/bs.po
odoo_addons/account_invoice_rounding/i18n/ca.po
odoo_addons/account_invoice_rounding/i18n/cs.po
odoo_addons/account_invoice_rounding/i18n/da.po
odoo_addons/account_invoice_rounding/i18n/de.po
odoo_addons/account_invoice_rounding/i18n/el_GR.po
odoo_addons/account_invoice_rounding/i18n/en_GB.po
odoo_addons/account_invoice_rounding/i18n/es.po
odoo_addons/account_invoice_rounding/i18n/es_CR.po
odoo_addons/account_invoice_rounding/i18n/es_EC.po
odoo_addons/account_invoice_rounding/i18n/es_MX.po
odoo_addons/account_invoice_rounding/i18n/es_PE.po
odoo_addons/account_invoice_rounding/i18n/es_VE.po
odoo_addons/account_invoice_rounding/i18n/et.po
odoo_addons/account_invoice_rounding/i18n/eu.po
odoo_addons/account_invoice_rounding/i18n/fi.po
odoo_addons/account_invoice_rounding/i18n/fr.po
odoo_addons/account_invoice_rounding/i18n/fr_CA.po
odoo_addons/account_invoice_rounding/i18n/fr_CH.po
odoo_addons/account_invoice_rounding/i18n/fr_FR.po
odoo_addons/account_invoice_rounding/i18n/gl.po
